LICENSE
MANIFEST.in
Pipfile
Pipfile.lock
README.rst
pytest.ini
setup.py
spacedr/__init__.py
spacedr/__version__.py
spacedr/db.py
spacedr/errors.py
spacedr/port.py
spacedr/schedule.py
spacedr/spacedr.py
spacedr.egg-info/PKG-INFO
spacedr.egg-info/SOURCES.txt
spacedr.egg-info/dependency_links.txt
spacedr.egg-info/requires.txt
spacedr.egg-info/top_level.txt
tests/__init__.py
tests/conftest.py
tests/test_spacedr.py