Metadata-Version: 1.2
Name: spacedr
Version: 1.0.1
Summary: Spaced Repetition API
Home-page: http://github.com/sttlr/spacedr
Author: sttlr
License: MIT
Platform: UNKNOWN
Classifier: License :: OSI Approved :: MIT License
Classifier: Programming Language :: Python
Classifier: Programming Language :: Python :: 3.5
Classifier: Programming Language :: Python :: 3.7
Classifier: Programming Language :: Python :: Implementation :: CPython
Classifier: Programming Language :: Python :: Implementation :: PyPy
Requires-Python: >=3.5
